lusid_workflow/__init__.py
lusid_workflow/api/__init__.py
lusid_workflow/api/action_logs_api.py
lusid_workflow/api/application_metadata_api.py
lusid_workflow/api/event_handlers_api.py
lusid_workflow/api/task_definitions_api.py
lusid_workflow/api/tasks_api.py
lusid_workflow/api/workers_api.py
lusid_workflow/api_client.py
lusid_workflow/api_response.py
lusid_workflow/configuration.py
lusid_workflow/exceptions.py
lusid_workflow/extensions/__init__.py
lusid_workflow/extensions/api_client.py
lusid_workflow/extensions/api_client_factory.py
lusid_workflow/extensions/api_configuration.py
lusid_workflow/extensions/configuration_loaders.py
lusid_workflow/extensions/configuration_options.py
lusid_workflow/extensions/file_access_token.py
lusid_workflow/extensions/proxy_config.py
lusid_workflow/extensions/refreshing_token.py
lusid_workflow/extensions/rest.py
lusid_workflow/extensions/retry.py
lusid_workflow/extensions/socket_keep_alive.py
lusid_workflow/extensions/tcp_keep_alive_connector.py
lusid_workflow/models/__init__.py
lusid_workflow/models/access_controlled_action.py
lusid_workflow/models/access_controlled_resource.py
lusid_workflow/models/action_definition.py
lusid_workflow/models/action_definition_response.py
lusid_workflow/models/action_details.py
lusid_workflow/models/action_details_response.py
lusid_workflow/models/action_id.py
lusid_workflow/models/action_log.py
lusid_workflow/models/action_log_item.py
lusid_workflow/models/action_log_origin.py
lusid_workflow/models/batch_update_tasks_request.py
lusid_workflow/models/batch_update_tasks_response.py
lusid_workflow/models/calendar_reference.py
lusid_workflow/models/change_item.py
lusid_workflow/models/create_child_task_configuration.py
lusid_workflow/models/create_child_tasks_action.py
lusid_workflow/models/create_child_tasks_action_response.py
lusid_workflow/models/create_event_handler_request.py
lusid_workflow/models/create_new_task_activity.py
lusid_workflow/models/create_new_task_activity_response.py
lusid_workflow_sdk-2.3.1.dist-info/METADATA
lusid_workflow_sdk-2.3.1.dist-info/WHEEL
lusid_workflow_sdk-2.3.1.dist-info/RECORD
